{
  "id": {
    "attribute": null,

    "by": null,
    "selector": null,

    "use_mouse": false,
    "mandatory": true,
    "action": null,
    "@note": ""
  },
  "id_manufacturer": {
    "attribute": null,

    "by": null,
    "selector": null,

    "use_mouse": false,
    "mandatory": true,
    "action": null,
    "@note": ""
  },
  "id_supplier": {
    "attribute": "11267",

    "by": "VALUE",
    "selector": null,

    "use_mouse": false,
    "mandatory": true,
    "action": null,
    "@note": ""
  },
  "id_category_default": {
    "attribute": null,
    "by": null,
    "selector": null,

    "use_mouse": false,
    "mandatory": true,
    "action": null,
    "@note": ""
  },
  "new": {
    "attribute": true,

    "by": "VALUE",
    "selector": null,

    "use_mouse": false,
    "mandatory": true,
    "action": null
  },
  "cache_default_attribute": {
    "attribute": null,

    "by": null,
    "selector": null,

    "use_mouse": false,
    "mandatory": true,
    "action": null,
    "@note": ""
  },
  "url_default_image": {
    "attribute": "href",

    "by": "XPATH",
    "selector": "//div[contains(@class,'woocommerce-product-gallery__image')]/a",

    "use_mouse": false,
    "mandatory": true,
    "action": null,
    "@note": ""
  },
  "id_default_combination": {
    "attribute": null,

    "by": null,
    "selector": null,

    "use_mouse": false,
    "mandatory": true,
    "action": null,
    "@note": ""
  },
  "id_tax": {
    "attribute": null,

    "by": null,
    "selector": null,

    "use_mouse": false,
    "mandatory": true,
    "action": null,
    "@note": ""
  },
  "position_in_category": {
    "attribute": null,

    "by": null,
    "selector": null,

    "use_mouse": false,
    "mandatory": true,
    "action": null,
    "@note": ""
  },
  "type": {
    "attribute": null,

    "by": null,
    "selector": null,

    "use_mouse": false,
    "mandatory": true,
    "action": null,
    "@note": ""
  },
  "id_shop_default": {
    "attribute": null,
    "by": null,
    "selector": null,
    "use_mouse": false,
    "mandatory": true,
    "action": null,
    "@note": ""
  },
  "product_reference_and_volume_and_price_for_100": {
    "attribute": null,
    "by": "XPATH",
    "selector": "//div[@data-widget_type='shortcode.default']",
    "use_mouse": false,
    "mandatory": true,
    "action": null,
    "@note": "\u041d\u0430 \u0441\u0430\u0439\u0442\u0435 \u043a\u0440\u0438\u0432\u043e\u0439 HTML, \u043f\u043e\u044d\u0442\u043e\u043c\u0443 \u043e\u0434\u043d\u0438\u043c \u043b\u043e\u043a\u0430\u0442\u043e\u0440\u043e\u043c \u0432\u044b\u0442\u0435\u0441\u043a\u0438\u0432\u0430\u044e 3 \u0437\u043d\u0430\u0447\u0435\u043d\u0438\u044f, \u0430 \u043f\u043e\u0442\u043e\u043c \u0434\u0435\u043b\u0430\u044e \u043f\u0430\u0440\u0441\u0438\u043d\u0433. \u041f\u0440\u0438\u0445\u043e\u0434\u0438\u0442 \u0441\u043f\u0438\u0441\u043e\u043a \u0438\u0437 \u0447\u0435\u0442\u044b\u0440\u0435\u0445 \u043e\u0431\u044a\u0435\u043a\u0442\u043e\u0432: \u043e\u0431\u044a\u0435\u043c, \u0446\u0435\u043d\u0430 \u0437\u0430 100 \u0433\u0440, \u0430\u0440\u0442\u0438\u043a\u0443\u043b, \u043f\u0443\u0441\u0442\u043e\u0439 div"
  },
  "reference": {
    "attribute": null,
    "by": "XPATH",
    "selector": "//div[@data-widget_type='shortcode.default']",
    "use_mouse": false,
    "mandatory": true,
    "action": null,
    "@note": "ps_product.refernce \u0437\u0434\u0435\u0441\u044c \u044f \u043f\u044b\u0442\u0430\u044e\u0441\u044c \u0432\u044b\u0442\u0430\u0449\u0438\u0442\u044c \u0447\u0435\u0440\u0435\u0437 \u0430\u0442\u0442\u0440\u0438\u0431\u0443\u0442 \u043f\u0435\u0440\u0435\u0434\u0430\u043d\u043d\u044b\u0439 \u0432 \u0441\u0435\u043b\u0435\u043a\u0442\u043e\u0440\u0435"
  },
  "supplier_reference": {
    "attribute": "innerText",
    "by": "XPATH",
    "selector": "",
    "logic for action[AND|OR|XOR|VALUE|null]": "TAKE 3 ELEMENT FROM ARRAY",
    "use_mouse": false,
    "mandatory": true,
    "action": null,
    "@note": "\u0437\u0430\u0431\u0438\u0440\u0430\u0435\u0442 3 \u044d\u043b\u0435\u043c\u0435\u043d\u0442\u0430 \u0441\u043e \u0441\u0442\u0440\u0430\u043d\u0438\u0446\u044b"
  },
  "location": {
    "attribute": null,
    "by": null,
    "selector": null,
    "use_mouse": false,
    "mandatory": true,
    "action": null,
    "@note": ""
  },
  "width": {
    "attribute": null,
    "by": null,
    "selector": null,
    "use_mouse": false,
    "mandatory": true,
    "action": null,
    "@note": ""
  },
  "height": {
    "attribute": null,
    "by": null,
    "selector": null,

    "use_mouse": false,
    "mandatory": true,
    "action": null,
    "@note": ""
  },
  "depth": {
    "attribute": null,

    "by": null,
    "selector": null,

    "use_mouse": false,
    "mandatory": true,
    "action": null,
    "@note": ""
  },
  "weight": {
    "attribute": "innerText",

    "by": "XPATH",
    "selector": "//div[@data-widget_type='shortcode.default']",
    "logic for action[AND|OR|XOR|VALUE|null]": "TAKE 2 ELEMENT FROM ARRAY",
    "use_mouse": false,
    "mandatory": true,
    "action": null,
    "@note": ""
  },
  "quantity_discount": {
    "attribute": null,

    "by": null,
    "selector": null,

    "use_mouse": false,
    "mandatory": true,
    "action": null,
    "@note": ""
  },
  "ean13": {
    "attribute": null,

    "by": null,
    "selector": null,

    "use_mouse": false,
    "mandatory": true,
    "action": null,
    "@note": ""
  },
  "isbn": {
    "attribute": null,

    "by": null,
    "selector": null,

    "use_mouse": false,
    "mandatory": true,
    "action": null,
    "@note": ""
  },
  "upc": {
    "attribute": null,

    "by": null,
    "selector": null,

    "use_mouse": false,
    "mandatory": true,
    "action": null,
    "@note": ""
  },
  "mpn": {
    "attribute": null,

    "by": null,
    "selector": null,

    "use_mouse": false,
    "mandatory": true,
    "action": null,
    "@note": ""
  },
  "cache_is_pack": {
    "attribute": null,

    "by": null,
    "selector": null,

    "use_mouse": false,
    "mandatory": true,
    "action": null,
    "@note": ""
  },
  "cache_has_attachments": {
    "attribute": null,

    "by": null,
    "selector": null,

    "use_mouse": false,
    "mandatory": true,
    "action": null,
    "@note": ""
  },
  "is_virtual": {
    "attribute": null,

    "by": null,
    "selector": null,

    "use_mouse": false,
    "mandatory": true,
    "action": null,
    "@note": ""
  },
  "state": {
    "attribute": null,

    "by": null,
    "selector": null,

    "use_mouse": false,
    "mandatory": true,
    "action": null,
    "@note": ""
  },
  "additional_delivery_times": {
    "attribute": null,

    "by": null,
    "selector": null,

    "use_mouse": false,
    "mandatory": true,
    "action": null
  },
  "delivery_in_stock": {
    "attribute": "Israel Post",

    "by": "VALUE",
    "selector": null,

    "use_mouse": false,
    "mandatory": true,
    "action": null,
    "@note": ""
  },
  "delivery_out_stock": {
    "attribute": null,

    "by": "XPATH",
    "selector": "//p[contains(@class, 'out-of-stock')]",

    "use_mouse": false,
    "mandatory": true,
    "action": null,
    "@note": ""
  },
  "product_type": {
    "attribute": null,

    "by": null,
    "selector": null,

    "use_mouse": false,
    "mandatory": true,
    "action": null,
    "@note": ""
  },
  "on_sale": {
    "attribute": null,

    "by": null,
    "selector": null,

    "use_mouse": false,
    "mandatory": true,
    "action": null,
    "@note": ""
  },
  "online_only": {
    "attribute": null,

    "by": null,
    "selector": null,

    "use_mouse": false,
    "mandatory": true,
    "action": null,
    "@note": ""
  },
  "ecotax": {
    "attribute": null,

    "by": null,
    "selector": null,

    "use_mouse": false,
    "mandatory": true,
    "action": null,
    "@note": ""
  },
  "minimal_quantity": {
    "attribute": null,

    "by": null,
    "selector": null,

    "use_mouse": false,
    "mandatory": true,
    "action": null,
    "@note": ""
  },
  "low_stock_threshold": {
    "attribute": null,

    "by": null,
    "selector": null,

    "use_mouse": false,
    "mandatory": true,
    "action": null,
    "@note": ""
  },
  "low_stock_alert": {
    "attribute": null,

    "by": null,
    "selector": null,

    "use_mouse": false,
    "mandatory": true,
    "action": null,
    "@note": ""
  },
  "price": {
    "attribute": "innerText",

    "by": "XPATH",
    "selector": "//p[@class='price']",

    "use_mouse": false,
    "mandatory": true,
    "action": null,
    "@note": ""
  },
  "wholesale_price": {
    "attribute": null,

    "by": null,
    "selector": null,

    "use_mouse": false,
    "mandatory": true,
    "action": null,
    "@note": ""
  },
  "unity": {
    "attribute": null,

    "by": null,
    "selector": null,

    "use_mouse": false,
    "mandatory": true,
    "action": null,
    "@note": ""
  },
  "unit_price_ratio": {
    "attribute": null,

    "by": null,
    "selector": null,

    "use_mouse": false,
    "mandatory": true,
    "action": null,
    "@note": ""
  },
  "additional_shipping_cost": {
    "attribute": 30,

    "by": "VALUE",
    "selector": null,

    "use_mouse": false,
    "mandatory": true,
    "action": null,
    "@note": "Стоимость отправки. 30 шек. by: VALUE означает, что я беру значение из attribute"
  },
  "customizable": {
    "attribute": null,

    "by": null,
    "selector": null,

    "use_mouse": false,
    "mandatory": true,
    "action": null,
    "@note": ""
  },
  "text_fields": {
    "attribute": null,

    "by": null,
    "selector": null,

    "use_mouse": false,
    "mandatory": true,
    "action": null,
    "@note": ""
  },
  "uploadable_files": {
    "attribute": null,

    "by": null,
    "selector": null,

    "use_mouse": false,
    "mandatory": true,
    "action": null,
    "@note": ""
  },
  "active": {
    "attribute": null,

    "by": null,
    "selector": null,

    "use_mouse": false,
    "mandatory": true,
    "action": null,
    "@note": ""
  },
  "redirect_type": {
    "attribute": null,

    "by": null,
    "selector": null,

    "use_mouse": false,
    "mandatory": true,
    "action": null,
    "@note": ""
  },
  "id_type_redirected": {
    "attribute": null,

    "by": null,
    "selector": null,

    "use_mouse": false,
    "mandatory": true,
    "action": null,
    "@note": ""
  },
  "available_for_order": {
    "attribute": null,

    "by": null,
    "selector": null,

    "use_mouse": false,
    "mandatory": true,
    "action": null,
    "@note": ""
  },
  "available_date": {
    "attribute": null,

    "by": null,
    "selector": null,

    "use_mouse": false,
    "mandatory": true,
    "action": null,
    "@note": ""
  },
  "show_price": {
    "attribute": null,

    "by": null,
    "selector": null,

    "use_mouse": false,
    "mandatory": true,
    "action": null,
    "@note": ""
  },
  "indexed": {
    "attribute": null,

    "by": null,
    "selector": null,

    "use_mouse": false,
    "mandatory": true,
    "action": null,
    "@note": ""
  },
  "visibility": {
    "attribute": null,

    "by": null,
    "selector": null,

    "use_mouse": false,
    "mandatory": true,
    "action": null,
    "@note": ""
  },
  "advanced_stock_management": {
    "attribute": null,

    "by": null,
    "selector": null,

    "use_mouse": false,
    "mandatory": true,
    "action": null,
    "@note": ""
  },
  "date_add": {
    "attribute": null,

    "by": null,
    "selector": null,

    "use_mouse": false,
    "mandatory": true,
    "action": null,
    "@note": ""
  },
  "date_upd": {
    "attribute": null,

    "by": null,
    "selector": null,

    "use_mouse": false,
    "mandatory": true,
    "action": null,
    "@note": ""
  },
  "pack_stock_type": {
    "attribute": null,

    "by": null,
    "selector": null,

    "use_mouse": false,
    "mandatory": true,
    "action": null
  },
  "meta_description": {
    "attribute": null,

    "by": null,
    "selector": null,

    "use_mouse": false,
    "mandatory": true,
    "action": null
  },
  "meta_keywords": {
    "attribute": null,

    "by": null,
    "selector": null,

    "use_mouse": false,
    "mandatory": true,
    "action": null
  },
  "meta_title": {
    "attribute": null,

    "by": null,
    "selector": null,

    "use_mouse": false,
    "mandatory": true,
    "action": null
  },
  "link_rewrite": {
    "attribute": null,

    "by": null,
    "selector": null,

    "use_mouse": false,
    "mandatory": true,
    "action": null
  },
  "name": {
    "attribute": "innerText",

    "by": "XPATH",
    "selector": "//h1[contains(@class,'product_title')]",

    "use_mouse": false,
    "mandatory": true,
    "action": null
  },
  "description": {
    "attribute": null,

    "by": "XPATH",
    "selector": "//div[@id = 'tab-description']//p",

    "action": null,
    "use_mouse": false,
    "mandatory": true,
    "@note": ""
  },
  "description_short": {
    "attribute": "innerText",


    "by": "XPATH",
    "selector": "//div[@id = 'tab-description']//p",

    "use_mouse": false,
    "mandatory": true,
    "action": null,
    "@note": "на сайте есть только description. "
  },

  "affiliate_short_link": {
    "attribute": "$_(driver.current_url)_$",

    "by": "VALUE",
    "selector": null,

    "use_mouse": false,
    "mandatory": true,
    "action": null
  },
  "affiliate_text": {
    "attribute": null,

    "by": null,
    "selector": null,

    "use_mouse": false,
    "mandatory": true,
    "action": null
  },
  "affiliate_summary": {
    "attribute": null,

    "by": null,
    "selector": null,

    "use_mouse": false,
    "mandatory": true,
    "action": null
  },
  "affiliate_summary_2": {
    "attribute": null,

    "by": null,
    "selector": null,

    "use_mouse": false,
    "mandatory": true,
    "action": null
  },
  "affiliate_image_small": {
    "attribute": null,

    "by": null,
    "selector": null,

    "use_mouse": false,
    "mandatory": true,
    "action": null
  },
  "affiliate_image_medium": {
    "attribute": null,

    "by": null,
    "selector": null,

    "use_mouse": false,
    "mandatory": true,
    "action": null
  },
  "affiliate_image_large": {
    "attribute": null,

    "by": null,
    "selector": null,

    "use_mouse": false,
    "mandatory": true,
    "action": null
  },
  "ingridients": {
    "attribute": null,

    "by": null,
    "selector": "//div[contains(@id ,'מרכיבים'])//p",

    "use_mouse": false,
    "mandatory": true,
    "action": null
  },

  "how_to_use": {
    "attribute": [ null, null ],
    "by": [ "XPATH", "XPATH" ],
    "selector": [ "//a[contains(@href, 'אופן-השימוש')]", "//div[contains(@id ,'אופן-השימוש')]//p" ],
    "use_mouse": [ false, false ],
    "mandatory": [ true, true ],
    "action": [ "click()", null ],
    "@note": [ null, null ]
  },

  "spcecification": {
    "attribute": null,

    "by": null,
    "selector": null,

    "use_mouse": false,
    "mandatory": true,
    "action": null
  },

  "available_now": {
    "attribute": null,

    "by": null,
    "selector": null,

    "use_mouse": false,
    "mandatory": true,
    "action": null
  },
  "available_later": {
    "attribute": null,

    "by": null,
    "selector": null,

    "use_mouse": false,
    "mandatory": true,
    "action": null
  },
  "associations": {
    "attribute": null,

    "by": null,
    "selector": null,

    "use_mouse": false,
    "mandatory": true,
    "action": null
  },
  "Active (0/1)": {
    "attribute": null,

    "by": null,
    "selector": null,

    "use_mouse": false,
    "mandatory": true,
    "action": null
  },
  "Categories (x,y,z...)": "2,",
  "Price tax excluded": {
    "attribute": null,

    "by": null,
    "selector": null,

    "use_mouse": false,
    "mandatory": true,
    "action": null
  },
  "Price tax included": {
    "attribute": null,

    "by": null,
    "selector": null,

    "use_mouse": false,
    "mandatory": true,
    "action": null
  },
  "Tax rule ID": {
    "attribute": null,

    "by": null,
    "selector": null,

    "use_mouse": false,
    "mandatory": true,
    "action": null
  },
  "Cost price": {
    "attribute": null,

    "by": null,
    "selector": null,

    "use_mouse": false,
    "mandatory": true,
    "action": null
  },
  "On sale (0/1)": {
    "attribute": null,

    "by": null,
    "selector": null,

    "use_mouse": false,
    "mandatory": true,
    "action": null
  },
  "Discount amount": {
    "attribute": null,

    "by": null,
    "selector": null,

    "use_mouse": false,
    "mandatory": true,
    "action": null
  },
  "Discount percent": {
    "attribute": null,

    "by": null,
    "selector": null,

    "use_mouse": false,
    "mandatory": true,
    "action": null
  },
  "Discount from (yyyy-mm-dd)": {
    "attribute": null,

    "by": null,
    "selector": null,

    "use_mouse": false,
    "mandatory": true,
    "action": null
  },
  "Discount to (yyyy-mm-dd)": {
    "attribute": null,

    "by": null,
    "selector": null,

    "use_mouse": false,
    "mandatory": true,
    "action": null
  },
  "Supplier": {
    "attribute": "",

    "by": null,
    "selector": null,

    "use_mouse": false,
    "mandatory": true,
    "action": null
  },
  "Brand": {
    "attribute": null,

    "by": null,
    "selector": null,

    "use_mouse": false,
    "mandatory": true,
    "action": null
  },
  "EAN13": {
    "attribute": null,

    "by": null,
    "selector": null,

    "use_mouse": false,
    "mandatory": true,
    "action": null
  },
  "UPC": {
    "attribute": null,

    "by": null,
    "selector": null,

    "use_mouse": false,
    "mandatory": true,
    "action": null
  },
  "MPN": {
    "attribute": null,

    "by": null,
    "selector": null,

    "use_mouse": false,
    "mandatory": true,
    "action": null
  },
  "Ecotax": {
    "attribute": null,

    "by": null,
    "selector": null,

    "use_mouse": false,
    "mandatory": true,
    "action": null
  },
  "Width": {
    "attribute": null,

    "by": null,
    "selector": null,

    "use_mouse": false,
    "mandatory": true,
    "action": null
  },
  "Height": {
    "attribute": null,

    "by": null,
    "selector": null,

    "use_mouse": false,
    "mandatory": true,
    "action": null
  },
  "Depth": {
    "attribute": null,

    "by": null,
    "selector": null,

    "use_mouse": false,
    "mandatory": true,
    "action": null
  },
  "Weight": {
    "attribute": null,

    "by": null,
    "selector": null,

    "use_mouse": false,
    "mandatory": true,
    "action": null
  },
  "Delivery time of in-stock products:": {
    "attribute": null,

    "by": null,
    "selector": null,

    "use_mouse": false,
    "mandatory": true,
    "action": null
  },
  "Delivery time of out-of-stock products with allowed orders:": {
    "attribute": null,

    "by": null,
    "selector": null,

    "use_mouse": false,
    "mandatory": true,
    "action": null
  },
  "Quantity": {
    "attribute": null,

    "by": null,
    "selector": null,

    "use_mouse": false,
    "mandatory": true,
    "action": null
  },
  "Minimal quantity": {
    "attribute": null,

    "by": null,
    "selector": null,

    "use_mouse": false,
    "mandatory": true,
    "action": null
  },
  "Low stock level": {
    "attribute": null,

    "by": null,
    "selector": null,

    "use_mouse": false,
    "mandatory": true,
    "action": null
  },
  "Send me an email when the quantity is under this level": {
    "attribute": null,

    "by": null,
    "selector": null,

    "use_mouse": false,
    "mandatory": true,
    "action": null
  },
  "Tags (x,y,z...)": {
    "attribute": null,

    "by": null,
    "selector": null,

    "use_mouse": false,
    "mandatory": true,
    "action": null
  },
  "Meta title": {
    "attribute": null,

    "by": null,
    "selector": null,

    "use_mouse": false,
    "mandatory": true,
    "action": null
  },
  "Meta keywords": {
    "attribute": null,

    "by": null,
    "selector": null,

    "use_mouse": false,
    "mandatory": true,
    "action": null
  },
  "Meta description": {
    "attribute": null,

    "by": null,
    "selector": null,

    "use_mouse": false,
    "mandatory": true,
    "action": null
  },
  "Rewritten URL": {
    "attribute": null,

    "by": null,
    "selector": null,

    "use_mouse": false,
    "mandatory": true,
    "action": null
  },
  "Label when in stock": {
    "attribute": null,

    "by": null,
    "selector": null,

    "use_mouse": false,
    "mandatory": true,
    "action": null
  },
  "Label when backorder allowed": {
    "attribute": null,

    "by": null,
    "selector": null,

    "use_mouse": false,
    "mandatory": true,
    "action": null
  },
  "Available for order (0 = No, 1 = Yes)": {
    "attribute": null,

    "by": null,
    "selector": null,

    "use_mouse": false,
    "mandatory": true,
    "action": null
  },
  "Product availability date": {
    "attribute": null,

    "by": null,
    "selector": null,

    "use_mouse": false,
    "mandatory": true,
    "action": null
  },
  "Product creation date": {
    "attribute": null,

    "by": null,
    "selector": null,

    "use_mouse": false,
    "mandatory": true,
    "action": null
  },
  "Show price (0 = No, 1 = Yes)": {
    "attribute": null,

    "by": null,
    "selector": null,

    "use_mouse": false,
    "mandatory": true,
    "action": null
  },
  "Screenshot": {
    "attribute": null,

    "by": null,
    "selector": null,
    "use_mouse": false,
    "mandatory": true,
    "action": "screenshot()",
    "logic for action[AND|OR|XOR|VALUE|null]": null
  },
  "Image URLs (x,y,z...)": {
    "attribute": "src",

    "by": "XPATH",
    "selector": "//img[@class='product-gallery--loaded-image']",

    "use_mouse": false,
    "mandatory": true,
    "action": null
  },
  "Image alt texts (x,y,z...)": {
    "attribute": null,

    "by": null,
    "selector": null,

    "use_mouse": false,
    "mandatory": true,
    "action": null
  },
  "Delete existing images (0 = No, 1 = Yes)": {
    "attribute": null,

    "by": null,
    "selector": null,

    "use_mouse": false,
    "mandatory": true,
    "action": null
  },
  "Feature (Name:Value:Position:Customized)": {
    "attribute": null,

    "by": null,
    "selector": null,

    "use_mouse": false,
    "mandatory": true,
    "action": null
  },
  "Available online only (0 = No, 1 = Yes)": {
    "attribute": null,

    "by": null,
    "selector": null,

    "use_mouse": false,
    "mandatory": true,
    "action": null
  },
  "Condition": {
    "attribute": "new",

    "by": "VALUE",
    "selector": null,

    "use_mouse": false,
    "mandatory": true,
    "action": null
  },
  "Customizable (0 = No, 1 = Yes)": {
    "attribute": null,

    "by": null,
    "selector": null,

    "use_mouse": false,
    "mandatory": true,
    "action": null
  },
  "Uploadable files (0 = No, 1 = Yes)": {
    "attribute": null,

    "by": null,
    "selector": null,

    "use_mouse": false,
    "mandatory": true,
    "action": null
  },
  "Text fields (0 = No, 1 = Yes)": {
    "attribute": null,

    "by": null,
    "selector": null,

    "use_mouse": false,
    "mandatory": true,
    "action": null
  },
  "Action when out of stock": {
    "attribute": null,

    "by": null,
    "selector": null,

    "use_mouse": false,
    "mandatory": true,
    "action": null
  },
  "Virtual product (0 = No, 1 = Yes)": {
    "attribute": 0,

    "by": "VALUE",
    "selector": null,

    "use_mouse": false,
    "mandatory": true,
    "action": null
  },
  "File URL": {
    "attribute": null,

    "by": null,
    "selector": null,

    "use_mouse": false,
    "mandatory": true,
    "action": null
  },
  "Number of allowed downloads": {
    "attribute": null,

    "by": null,
    "selector": null,

    "use_mouse": false,
    "mandatory": true,
    "action": null
  },
  "Expiration date (yyyy-mm-dd)": {
    "attribute": null,

    "by": null,
    "selector": null,

    "use_mouse": false,
    "mandatory": true,
    "action": null
  },
  "Number of days": {
    "attribute": null,

    "by": null,
    "selector": null,

    "use_mouse": false,
    "mandatory": true,
    "action": null
  },
  "Advanced Stock Management": {
    "attribute": null,

    "by": null,
    "selector": null,

    "use_mouse": false,
    "mandatory": true,
    "action": null
  },
  "Depends on stock": {
    "attribute": null,

    "by": null,
    "selector": null,

    "use_mouse": false,
    "mandatory": true,
    "action": null
  },
  "Warehouse": {
    "attribute": null,

    "by": null,
    "selector": null,

    "use_mouse": false,
    "mandatory": true,
    "action": null
  },
  "Accessories (x,y,z...)": {
    "attribute": null,

    "by": null,
    "selector": null,

    "use_mouse": false,
    "mandatory": true,
    "action": null
  },
  "Open AI Product Description": {
    "attribute": null,

    "by": null,
    "selector": null,

    "use_mouse": false,
    "mandatory": true,
    "action": null
  },
  "Byer protection": {
    "attribute": null,

    "by": null,
    "selector": null,

    "use_mouse": false,
    "mandatory": true,
    "action": null
  },
  "Specification": {
    "attribute": null,

    "by": null,
    "selector": null,

    "use_mouse": false,
    "mandatory": true,
    "action": null
  },
  "Refirbished product description": {
    "attribute": null,

    "by": null,
    "selector": null,

    "use_mouse": false,
    "mandatory": true,
    "action": null
  },
  "Additional shipping details": {
    "attribute": null,

    "by": null,
    "selector": null,

    "use_mouse": false,
    "mandatory": true,
    "action": null
  }
}